{
    "manifest": {
        "name": "Emilia summer",
        "license": "©re:zero los",
        "version": "0.3.1",
        "author": "wind",
        "updater": "https:\/\/github.com\/Drownbywind\/Aliu-Themes\/raw\/Emilia_summer_theme\/emilia_summer.json"
    },
    "background": {
        "url": "https:\/\/raw.githubusercontent.com\/Drownbywind\/Aliu-Themes\/Emilia_summer_theme\/emilia_summer_20_9.jpg",
        "overlay_alpha": 120
    },
    "fonts": {},
    "simple_colors": {
        "active_channel": 1922793921,
        "statusbar": 1275068416
    },
    "colors": {
        "primary_dark_400": -859979277,
        "primary_dark_100": -793865747,
        "primary_dark_300": -422328334,
        "primary_dark_360": -741486593,
        "primary_dark_200": -119084299,
        "primary_dark_630": 235866644,
        "primary_dark_600": 235931670,
        "primary_dark_800": 1695156491,
        "primary_dark_700": 234881024,
        "primary_dark_900": -889192448,
        "primary_dark_500": -16777216,
        "primary_dark_660": 2099518760,
        "uikit_btn_compound_color_selector_light": -263175562,
        "brand": -257124653,
        "brand_new_500": -256993581,
        "uikit_btn_compound_color_selector_dark": -256469293,
        "uikit_settings_item_text_color_dark": -422328334,
        "uikit_settings_item_text_color_light": -966239877,
        "primary_700": 1694498816,
        "white_800": -1474624988,
        "white_500": -420748289,
        "white": -234881025,
        "dim_foreground_material_light": -1072492267,
        "primary_dark_material_dark": 1695156491,
        "primary_500_alpha_20": 1627389952
    },
    "drawable_tints": {
        "ic_channel_text": -422328334,
        "ic_channel_text_nsfw": -422328334,
        "ic_channel_text_locked": -422328334,
        "ic_channel_lock_16dp": -422328334,
        "ic_channel_text_grey_18dp": -422328334,
        "ic_channel_voice_grey_18dp": -422328334,
        "ic_channel_announcements_thread_nsfw": -422328334,
        "ic_channel_announcements_thread_locked": -422328334,
        "ic_channel_announcements_thread": -422328334,
        "ic_channel_announcements_nsfw": -422328334,
        "ic_channel_announcements_locked": -422328334,
        "ic_channel_announcements_16dp": -422328334,
        "ic_channel_announcements": -422328334,
        "ic_sidebar_pins_on_dark_24dp": -422328334,
        "ic_sidebar_pins_off_dark_24dp": -422328334,
        "ic_sidebar_notifications_off_dark_24dp": -422328334,
        "ic_sidebar_notifications_on_dark_24dp": -422328334,
        "ic_arrow_right_24dp": -422328334,
        "ic_visibility_white_24dp": -422328334,
        "ic_content_copy_white_a60_24dp": -422328334,
        "ic_thread_white_24dp": -422328334,
        "ic_thread_grey_18dp": -422328334,
        "ic_sidebar_search_24dp": -422328334,
        "ic_notifications_white_a60_24dp": -422328334,
        "ic_notifications_off_white_a60_24dp": -422328334,
        "ic_notifications_settings_white_a60_24dp": -422328334,
        "img_logo_wordmark": -422328334,
        "drawable_button_red": -8888919,
        "drawable_button_grey": -14216914,
        "drawable_open_folder_light": -256595993,
        "ic_settings_white_a60_24dp": -422328334,
        "drawable_open_folder_dark": 1849038671
    },
    "raws": {}
}